create_project/__init__.py
create_project/__main__.py
create_project/create_project.py
create_project/gitlab_api.py
create_project/read_yaml.py
create_project/secret.py
create_project-0.5.1.dist-info/METADATA
create_project-0.5.1.dist-info/RECORD
create_project-0.5.1.dist-info/WHEEL
create_project-0.5.1.dist-info/entry_points.txt
create_project-0.5.1.dist-info/top_level.txt
test/__init__.py
test/test_create_complete_project.py
test/test_gitlab_api_functions.py
test/test_read_yaml.py
