Metadata-Version: 2.1
Name: create-project
Version: 0.5.1
Summary: Create a new project in gitlab with all your preferred     settings
Home-page: https://justine.kizhak.com/create_project.html
Author: Justine Kizhakkinedath
Author-email: justine@kizhak.com
License: UNKNOWN
Project-URL: Bug Reports, https://gitlab.com/justinekizhak/create_project/issues
Project-URL: Say Thanks!, http://saythanks.io/to/justinethomas
Project-URL: Source, https://gitlab.com/justinekizhak/create_project
Keywords: project creation
Platform: UNKNOWN
Classifier: Development Status :: 3 - Alpha
Classifier: Programming Language :: Python :: 3.6
Classifier: License :: OSI Approved :: MIT License
Classifier: Operating System :: OS Independent
